magic_lantern/__init__.py
magic_lantern/__main__.py
magic_lantern/album.py
magic_lantern/cli.py
magic_lantern/config.py
magic_lantern/controller.py
magic_lantern/log.py
magic_lantern/pdf.py
magic_lantern/screen.py
magic_lantern/signal.py
magic_lantern/slide.py
magic_lantern/slideshow.py
magic_lantern/text.py
magic_lantern-0.0.20.dist-info/METADATA
magic_lantern-0.0.20.dist-info/WHEEL
magic_lantern-0.0.20.dist-info/entry_points.txt
magic_lantern-0.0.20.dist-info/licenses/LICENSE
magic_lantern-0.0.20.dist-info/RECORD
