Metadata-Version: 2.4
Name: magic-lantern
Version: 0.0.20
Summary: A presentation tool for kiosks, digital signage, slide shows.
Project-URL: Homepage, https://github.com/normanlorrain/magic-lantern
Author-email: Norman Lorrain <normanlorrain@gmail.com>
License-File: LICENSE
Classifier: License :: OSI Approved :: MIT License
Classifier: Operating System :: OS Independent
Classifier: Programming Language :: Python :: 3
Requires-Python: >=3.11
Requires-Dist: click
Requires-Dist: exifread
Requires-Dist: pygame
Requires-Dist: pymupdf
